transparent_rotate/LICENSE
transparent_rotate/README.MD
transparent_rotate/__init__.py
transparent_rotate/requirements.txt
transparent_rotate/thirdparty.json
transparent_rotate-0.10.dist-info/LICENSE.rst
transparent_rotate-0.10.dist-info/METADATA
transparent_rotate-0.10.dist-info/WHEEL
transparent_rotate-0.10.dist-info/top_level.txt
transparent_rotate-0.10.dist-info/RECORD
